{
  "cant": 29,
  "pistas_musicales": [
    {
      "identificador": 1,
      "titulo": "Dancing Queen",
      "duracion": 352,
      "interprete": "ABBA"
    },
    {
      "identificador": 2,
      "titulo": "Uptown Funk",
      "duracion": 430,
      "interprete": "Mark Ronson ft. Bruno Mars"
    },
    {
      "identificador": 4,
      "titulo": "Can't Stop the Feeling!",
      "duracion": 356,
      "interprete": "Justin Timberlake"
    },
    {
      "identificador": 5,
      "titulo": "My Heart Will Go On",
      "duracion": 441,
      "interprete": "Celine Dion"
    },
    {
      "identificador": 6,
      "titulo": "I Will Always Love You",
      "duracion": 435,
      "interprete": "Whitney Houston"
    },
    {
      "identificador": 7,
      "titulo": "La Célula Que Explota",
      "duracion": 406,
      "interprete": "Café Tacuba"
    },
    {
      "identificador": 8,
      "titulo": "Mátame Suavemente",
      "duracion": 511,
      "interprete": "Jaguares"
    },
    {
      "identificador": 9,
      "titulo": "La Chispa Adecuada",
      "duracion": 422,
      "interprete": "Héroes del Silencio"
    },
    {
      "identificador": 10,
      "titulo": "Algo Está Cambiando",
      "duracion": 339,
      "interprete": "Julieta Venegas"
    },
    {
      "identificador": 11,
      "titulo": "El Sol No Regresa",
      "duracion": 415,
      "interprete": "La Quinta Estación"
    },
    {
      "identificador": 12,
      "titulo": "Me Gusta Todo de Ti",
      "duracion": 242,
      "interprete": "Banda Los Recoditos"
    },
    {
      "identificador": 13,
      "titulo": "Mientes",
      "duracion": 342,
      "interprete": "Camila"
    },
    {
      "identificador": 14,
      "titulo": "El Último Adiós",
      "duracion": 407,
      "interprete": "Paulina Rubio"
    },
    {
      "identificador": 15,
      "titulo": "Eres Mi Religión",
      "duracion": 407,
      "interprete": "Maná"
    },
    {
      "identificador": 16,
      "titulo": "Déjame Llorar",
      "duracion": 401,
      "interprete": "Ricardo Montaner"
    },
    {
      "identificador": 17,
      "titulo": "Persiana Americana",
      "duracion": 315,
      "interprete": "Soda Stereo"
    },
    {
      "identificador": 18,
      "titulo": "De Música Ligera",
      "duracion": 357,
      "interprete": "Soda Stereo"
    },
    {
      "identificador": 19,
      "titulo": "El Mató a un Policía Motorizado",
      "duracion": 344,
      "interprete": "Los Rodríguez"
    },
    {
      "identificador": 20,
      "titulo": "La Campana",
      "duracion": 403,
      "interprete": "El Tri"
    },
    {
      "identificador": 21,
      "titulo": "La Balsa",
      "duracion": 235,
      "interprete": "Los Gatos"
    },
    {
      "identificador": 22,
      "titulo": "La Pachanga",
      "duracion": 225,
      "interprete": "Vilma Palma e Vampiros"
    },
    {
      "identificador": 23,
      "titulo": "Yo Canibal",
      "duracion": 443,
      "interprete": "Patricio Rey y sus Redonditos de Ricota"
    },
    {
      "identificador": 24,
      "titulo": "La Bestia Pop",
      "duracion": 403,
      "interprete": "Los Redondos"
    },
    {
      "identificador": 25,
      "titulo": "El Mató a un Policía Motorizado",
      "duracion": 344,
      "interprete": "Los Rodríguez"
    },
    {
      "identificador": 26,
      "titulo": "Ji Ji Ji",
      "duracion": 413,
      "interprete": "Los Redondos"
    },
    {
      "identificador": 27,
      "titulo": "El Oso",
      "duracion": 539,
      "interprete": "Moris"
    },
    {
      "identificador": 28,
      "titulo": "Rasguña las Piedras",
      "duracion": 445,
      "interprete": "Sui Generis"
    },
    {
      "identificador": 29,
      "titulo": "Luzbelito",
      "duracion": 616,
      "interprete": "Los Redondos"
    }
  ]
}